Aminoapps/__init__.py
aminoapps-0.1.0.dist-info/METADATA
aminoapps-0.1.0.dist-info/WHEEL
aminoapps-0.1.0.dist-info/top_level.txt
aminoapps-0.1.0.dist-info/RECORD
