Metadata-Version: 2.4
Name: Aminoapps
Version: 0.1.0
Summary: The best
Author: ZOOM
License: MIT
Dynamic: author
Dynamic: license
Dynamic: summary
